pyphm/__init__.py
pyphm/datasets/__init__.py
pyphm/datasets/airbus.py
pyphm/datasets/ims.py
pyphm/datasets/milling.py
pyphm/datasets/pyphm.py
pyphm/datasets/utils.py
pyphm/datasets/auxilary_metadata/__init__.py
pyphm/datasets/auxilary_metadata/airbus_dfvalid_groundtruth.csv
pyphm/datasets/auxilary_metadata/milling_labels_with_tool_class.csv
pyphm-0.0.5.dist-info/LICENSE
pyphm-0.0.5.dist-info/METADATA
pyphm-0.0.5.dist-info/WHEEL
pyphm-0.0.5.dist-info/top_level.txt
pyphm-0.0.5.dist-info/RECORD
