Metadata-Version: 2.1
Name: pyphm
Version: 0.0.5
Summary: Machinery data, made easy
Home-page: https://github.com/tvhahn/PyPHM
Author: Tim von Hahn
Author-email: t.vonhahn@queensu.ca
Project-URL: Bug Tracker, https://github.com/tvhahn/PyPHM/issues
Classifier: Programming Language :: Python :: 3
Classifier: License :: OSI Approved :: MIT License
Classifier: Operating System :: OS Independent
Requires-Python: >=3.6
License-File: LICENSE
Requires-Dist: pandas
Requires-Dist: wheel
Requires-Dist: scipy
Requires-Dist: numpy
Requires-Dist: py7zr
Requires-Dist: rarfile
Requires-Dist: tqdm
Requires-Dist: requests
Requires-Dist: versioned-hdf5
Requires-Dist: h5py
Requires-Dist: tables
Requires-Dist: gdown
Provides-Extra: doc
Requires-Dist: sphinx (~=4.4.0) ; extra == 'doc'
Requires-Dist: myst-parser ; extra == 'doc'
